ctu_relational/__init__.py
ctu_relational/datasets/__init__.py
ctu_relational/datasets/ctu_dataset.py
ctu_relational/datasets/ctu_datasets.py
ctu_relational/datasets/dataset-info.csv
ctu_relational/datasets/db_dataset.py
ctu_relational/db/__init__.py
ctu_relational/db/column_types.py
ctu_relational/db/db_inspector.py
ctu_relational/tasks/__init__.py
ctu_relational/tasks/ctu_entity_task_base.py
ctu_relational/tasks/ctu_entity_task_classic.py
ctu_relational/tasks/ctu_entity_task_temporal.py
ctu_relational/tasks/ctu_link_task.py
ctu_relational/tasks/ctu_tasks.py
ctu_relational/tasks/task-info.csv
ctu_relational/utils/__init__.py
ctu_relational/utils/autodetect_schema.py
ctu_relational/utils/datetime.py
ctu_relational/utils/merge.py
ctu_relational-0.4.0.dist-info/licenses/LICENSE
ctu_relational-0.4.0.dist-info/WHEEL
ctu_relational-0.4.0.dist-info/METADATA
ctu_relational-0.4.0.dist-info/RECORD
