Metadata-Version: 2.4
Name: ctu_relational
Version: 0.4.0
Summary: CTU Relational: SQL Database Datasets for Machine Learning
Keywords: 
Author-email: Jakub Peleška <jakub.peleska@fel.cvut.cz>
Requires-Python: >=3.10
Classifier: License :: OSI Approved :: MIT License
License-File: LICENSE
Requires-Dist: relbench>=1.1.0
Requires-Dist: pandas>=2.2.3
Requires-Dist: pymysql>=1.1.1
Requires-Dist: sqlalchemy>=2.0.40
Requires-Dist: inflect>=7.5.0
Requires-Dist: tqdm>=4.67.1
Requires-Dist: torch>=2.6.0 ; extra == "cpu"
Requires-Dist: torchvision>=0.21.0 ; extra == "cpu"
Requires-Dist: torchaudio>=2.6.0 ; extra == "cpu"
Requires-Dist: pytorch-frame>=0.2.5 ; extra == "cpu"
Requires-Dist: torch-geometric>=2.6.1 ; extra == "cpu"
Requires-Dist: torch>=2.6.0 ; extra == "cu124"
Requires-Dist: torchvision>=0.21.0 ; extra == "cu124"
Requires-Dist: torchaudio>=2.6.0 ; extra == "cu124"
Requires-Dist: pytorch-frame>=0.2.5 ; extra == "cu124"
Requires-Dist: torch-geometric>=2.6.1 ; extra == "cu124"
Project-URL: Homepage, https://github.com/jakubpeleska/ctu-relational-py
Project-URL: Issues, https://github.com/jakubpeleska/ctu-relational-py/issues
Provides-Extra: cpu
Provides-Extra: cu124
